README.md
setup.py
IconProwl/IconProwl.py
IconProwl/__init__.py
IconProwl.egg-info/PKG-INFO
IconProwl.egg-info/SOURCES.txt
IconProwl.egg-info/dependency_links.txt
IconProwl.egg-info/requires.txt
IconProwl.egg-info/top_level.txt