Metadata-Version: 2.1
Name: IconProwl
Version: 1.1.1
Summary: IconProwl : An unofficial API for scraping images off IconFinder.com for web development.
Author: Vishal
Author-email: vishalvenkat2604@gmail.com
License: MIT
Keywords: conversion
Classifier: Development Status :: 3 - Alpha
Classifier: Intended Audience :: Developers
Classifier: License :: OSI Approved :: MIT License
Classifier: Programming Language :: Python :: 3
Requires-Dist: pillow
Requires-Dist: requests
Requires-Dist: beautifulsoup4
Requires-Dist: lxml
